mongotriggers/__init__.py
mongotriggers/__version__.py
mongotriggers/mongodtriggers.py
mongotriggers/mongotriggers.py
mongotriggers-2.0.1.dist-info/DESCRIPTION.rst
mongotriggers-2.0.1.dist-info/METADATA
mongotriggers-2.0.1.dist-info/RECORD
mongotriggers-2.0.1.dist-info/WHEEL
mongotriggers-2.0.1.dist-info/metadata.json
mongotriggers-2.0.1.dist-info/pbr.json
mongotriggers-2.0.1.dist-info/top_level.txt
