Metadata-Version: 1.1
Name: mongotriggers
Version: 2.0.1
Summary: livedata for MongoDB, similar to RDBM triggers or meteorjs livedata
Home-page: https://github.com/drorasaf/mongotriggers/
Author: Dror Asaf
Author-email: drorasaf87@gmail.com
License: BSD
Platform: UNKNOWN
Classifier: Development Status :: 4 - Beta
Classifier: Intended Audience :: Developers
Classifier: Operating System :: OS Independent
Classifier: Programming Language :: Python :: 2
Classifier: Programming Language :: Python :: 2.7
Classifier: Programming Language :: Python :: 3
Classifier: Programming Language :: Python :: 3.4
Classifier: Programming Language :: Python :: 3.5
Classifier: Programming Language :: Python :: Implementation :: CPython
Classifier: Programming Language :: Python :: Implementation :: PyPy
Classifier: Topic :: Database
